{
    "games": [
        {
            "slug": "levels",
            "backgroundColor": "#D5C389",
            "title_fr": "étagement",
            "title_en": "levels",
            "title_nl": "bluck",
            "img_presentation": "etagement.png"
        },
        {
            "slug": "toxic",
            "backgroundColor": "#FFB559",
            "title_fr": "toxique ?",
            "title_en": "toxic ?",
            "title_nl": "bluck ?",
            "img_presentation": "toxic.png"
        },
        {
            "slug": "memory",
            "backgroundColor": "#E8D262",
            "title_fr": "memory",
            "title_en": "memory",
            "title_nl": "bluck",
            "img_presentation": "memory.png"
        },
        {
            "slug": "guesswho",
            "backgroundColor": "#52774E",
            "title_fr": "qui est-ce ?",
            "title_en": "guess who ?",
            "title_nl": "bluck ?",
            "img_presentation": "quiestce.png"
        },
        {
            "slug": "quiz",
            "backgroundColor": "#E07CAD",
            "title_fr": "quiz",
            "title_en": "quiz",
            "title_nl": "bluck",
            "img_presentation": "quiz.png"
        }
    ]
}